pyumetric/__init__.py
pyumetric/provider/__init__.py
pyumetric/provider/exceptions.py
pyumetric/provider/newrelic.py
pyumetric/provider/utils.py
pyumetric-0.0.4.dist-info/LICENSE
pyumetric-0.0.4.dist-info/METADATA
pyumetric-0.0.4.dist-info/WHEEL
pyumetric-0.0.4.dist-info/top_level.txt
pyumetric-0.0.4.dist-info/RECORD
